apiverve_sunposition/__init__.py
apiverve_sunposition/apiClient.py
apiverve_sunposition/exceptions.py
apiverve_sunposition/setup.py
apiverve_sunposition/setup_dep.py
apiverve_sunposition/tests/__init__.py
apiverve_sunposition/tests/test_api.py
apiverve_sunposition-1.1.5.dist-info/LICENSE
apiverve_sunposition-1.1.5.dist-info/METADATA
apiverve_sunposition-1.1.5.dist-info/WHEEL
apiverve_sunposition-1.1.5.dist-info/top_level.txt
apiverve_sunposition-1.1.5.dist-info/RECORD
